Metadata-Version: 2.1
Name: lyyddsender
Version: 1.7
Summary: lyyddsendertools for lyy
Author: Devin & lyy
Author-email: 
License: MIT
License-File: LICENSE
